randquik/__init__.py
randquik/__main__.py
randquik/benchmark.py
randquik/cli.py
randquik/crypto.py
randquik/io.py
randquik/progress.py
randquik/stats.py
randquik/utils.py
randquik/workers.py
randquik-2.1.0.dist-info/METADATA
randquik-2.1.0.dist-info/WHEEL
randquik-2.1.0.dist-info/entry_points.txt
randquik-2.1.0.dist-info/RECORD
