Metadata-Version: 2.4
Name: randquik
Version: 2.1.0
Summary: CLI tool for extremely fast random bytes.
Project-URL: Homepage, https://git.zi.fi/LeoVasanko/randquik
Project-URL: Repository, https://github.com/LeoVasanko/randquik
Author: Leo Vasanko
Keywords: AEGIS,CSPRNG,benchmark,random,shred
Classifier: Development Status :: 5 - Production/Stable
Classifier: Environment :: Console
Classifier: Intended Audience :: Developers
Classifier: Intended Audience :: System Administrators
Classifier: Topic :: Security :: Cryptography
Classifier: Topic :: Utilities
Requires-Python: >=3.13
Requires-Dist: aeg>=0.4.3
